Metadata-Version: 2.1
Name: greet-human
Version: 1.0.0
Summary: This package is used to greet people.
Home-page: https://example.com
Author:  Prajol Shrestha
Author-email: prajolstha9@gmail.com
License: MIT
Keywords: human,greet
Classifier: Development Status :: 3 - Alpha
Classifier: Intended Audience :: Developers
Classifier: Topic :: Software Development :: Build Tools
Classifier: License :: OSI Approved :: MIT License
Classifier: Programming Language :: Python :: 3.10
